fs_node_hash/__init__.py
fs_node_hash/chunk_map.py
fs_node_hash/dir_hashing.py
fs_node_hash/file_hashing.py
fs_node_hash/fs_node_hashing.py
fs_node_hash/hash_buffer.py
fs_node_hash/track_hash_in_dict.py
fs_node_hash/util.py
fs_node_hash-0.0.3.dist-info/LICENSE.txt
fs_node_hash-0.0.3.dist-info/METADATA
fs_node_hash-0.0.3.dist-info/WHEEL
fs_node_hash-0.0.3.dist-info/top_level.txt
fs_node_hash-0.0.3.dist-info/RECORD
